{
	"ulid": "01GXXJ2X8V4EMA6Q5MAZR16N1P",
	"minTime": 1681365600000,
	"maxTime": 1681387200000,
	"stats": {
		"numSamples": 18955391,
		"numSeries": 10162,
		"numChunks": 158133
	},
	"compaction": {
		"level": 2,
		"sources": [
			"01GXWXFPT1ZWY94KZN81SEZKB0",
			"01GXX4BE22FKDRV3VKYAWWMKKD",
			"01GXXB75A1TYPJHSQX05F1XZ56"
		],
		"parents": [
			{
				"ulid": "01GXWXFPT1ZWY94KZN81SEZKB0",
				"minTime": 1681365600000,
				"maxTime": 1681372800000
			},
			{
				"ulid": "01GXX4BE22FKDRV3VKYAWWMKKD",
				"minTime": 1681372800000,
				"maxTime": 1681380000000
			},
			{
				"ulid": "01GXXB75A1TYPJHSQX05F1XZ56",
				"minTime": 1681380000000,
				"maxTime": 1681387200000
			}
		]
	},
	"version": 1
}